{"cameraMode":{"drawMode":0,"name":"Shaded","section":"Shading Mode"},"sceneLighting":true,"audioPlay":false,"sceneViewState":{"m_AlwaysRefresh":false,"showFog":true,"showSkybox":true,"showFlares":true,"showImageEffects":true,"showParticleSystems":true,"showVisualEffectGraphs":true,"m_FxEnabled":true},"in2DMode":false,"pivot":{"x":903.5357055664063,"y":472.11761474609377,"z":-330.5792236328125},"rotation":{"x":-0.100215382874012,"y":-0.022386090829968454,"z":0.00226685032248497,"w":-0.9947205781936646},"size":625.5257568359375,"orthographic":false}